sample_package/__init__.py
sample_package/_version.py
sample_package/main.py
sample_package_chanshing-0.0.0.post1.dist-info/LICENSE.md
sample_package_chanshing-0.0.0.post1.dist-info/METADATA
sample_package_chanshing-0.0.0.post1.dist-info/WHEEL
sample_package_chanshing-0.0.0.post1.dist-info/entry_points.txt
sample_package_chanshing-0.0.0.post1.dist-info/top_level.txt
sample_package_chanshing-0.0.0.post1.dist-info/RECORD
