Metadata-Version: 2.1
Name: sample-package-chanshing
Version: 0.0.0.post1
Summary: An example Python project
Home-page: https://github.com/chanshing/sample-package
Download-URL: https://github.com/chanshing/sample-package
Author: Shing Chan
Maintainer: Shing Chan
Maintainer-email: cshing.m@gmail.com
License: See LICENSE file.
Keywords: example,setuptools,versioneer
Classifier: Programming Language :: Python :: 3
Classifier: Topic :: Scientific/Engineering
Requires-Python: >=3.8, <4
License-File: LICENSE.md
Provides-Extra: dev
Requires-Dist: versioneer ; extra == 'dev'
Requires-Dist: twine ; extra == 'dev'
Requires-Dist: ipdb ; extra == 'dev'
Requires-Dist: flake8 ; extra == 'dev'
Requires-Dist: autopep8 ; extra == 'dev'
Provides-Extra: docs
Requires-Dist: sphinx (>=4.2) ; extra == 'docs'
Requires-Dist: sphinx-rtd-theme (>=1.0) ; extra == 'docs'
Requires-Dist: readthedocs-sphinx-search (>=0.1) ; extra == 'docs'
Requires-Dist: docutils (<0.18) ; extra == 'docs'
